dippy/core/__init__.py
dippy/core/api/__init__.py
dippy/core/api/api.py
dippy/core/api/bases.py
dippy/core/api/endpoint.py
dippy/core/api/request.py
dippy/core/caching/__init__.py
dippy/core/caching/bases.py
dippy/core/caching/cache.py
dippy/core/caching/cacheable.py
dippy/core/caching/manager.py
dippy/core/enums.py
dippy/core/events.py
dippy/core/gateway/__init__.py
dippy/core/gateway/bases.py
dippy/core/gateway/connection.py
dippy/core/gateway/heartbeat.py
dippy/core/gateway/payload.py
dippy/core/intents.py
dippy/core/interfaces/__init__.py
dippy/core/interfaces/channel.py
dippy/core/interfaces/guild.py
dippy/core/interfaces/member.py
dippy/core/interfaces/message.py
dippy/core/interfaces/user.py
dippy/core/models/__init__.py
dippy/core/models/activity.py
dippy/core/models/application.py
dippy/core/models/attachment.py
dippy/core/models/channel.py
dippy/core/models/client_status.py
dippy/core/models/embed.py
dippy/core/models/emoji.py
dippy/core/models/events.py
dippy/core/models/game.py
dippy/core/models/guild.py
dippy/core/models/interaction.py
dippy/core/models/member.py
dippy/core/models/message.py
dippy/core/models/model.py
dippy/core/models/overwrite.py
dippy/core/models/presence.py
dippy/core/models/reaction.py
dippy/core/models/role.py
dippy/core/models/sticker.py
dippy/core/models/team.py
dippy/core/models/team_member.py
dippy/core/models/user.py
dippy/core/models/voice_state.py
dippy/core/permissions.py
dippy/core/snowflake.py
dippy/core/timestamp.py
dippy/core/version.py
dippy.core-0.0.1a2.dist-info/LICENSE
dippy.core-0.0.1a2.dist-info/WHEEL
dippy.core-0.0.1a2.dist-info/METADATA
dippy.core-0.0.1a2.dist-info/RECORD
